pymcabc/__init__.py
pymcabc/constants.py
pymcabc/cross_section.py
pymcabc/decay_particle.py
pymcabc/detector.py
pymcabc/feynman_diagram.py
pymcabc/generate_event.py
pymcabc/identify_process.py
pymcabc/particle.py
pymcabc/plotting.py
pymcabc/save_events.py
pymcabc-1.1.dist-info/LICENSE
pymcabc-1.1.dist-info/METADATA
pymcabc-1.1.dist-info/WHEEL
pymcabc-1.1.dist-info/top_level.txt
pymcabc-1.1.dist-info/RECORD
